verilog/updownmod8_1.0/tmp/individual_19.sv
module individual_19(input wire clk, input wire rst, input wire sel, output reg [2:0] q);
always @(posedge clk) begin
if(rst == 1) begin
q = 3'b000;
end
else begin
case(sel)
1'b0: q = q+1;
1'b1: q = q-1;
endcase
end
end
endmodule

verilog/updownmod8_1.0/tmp/individual_18.sv
module individual_18(input wire clk, input wire rst, input wire sel, output reg [2:0] q);
always @(posedge clk) begin
if(rst == 1) begin
q = 3'b000;
end
else begin
case(sel)
1'b0: q = q+1;
1'b1: q = q+1;
endcase
end
end
endmodule

verilog/updownmod8_1.0/tmp/individual_17.sv
module individual_17(input wire clk, input wire rst, input wire sel, output reg [2:0] q);
always @(posedge clk) begin
if(rst == 1) begin
q = 3'b000;
end
else begin
case(sel)
1'b0: q = q+1;
1'b1: q = q-1;
endcase
end
end
endmodule

verilog/updownmod8_1.0/tmp/individual_16.sv
module individual_16(input wire clk, input wire rst, input wire sel, output reg [2:0] q);
always @(posedge clk) begin
if(rst == 1) begin
q = 3'b000;
end
else begin
case(sel)
1'b0: q = q+1;
1'b1: q = q-1;
endcase
end
end
endmodule

verilog/updownmod8_1.0/tmp/individual_15.sv
module individual_15(input wire clk, input wire rst, input wire sel, output reg [2:0] q);
always @(posedge clk) begin
if(rst == 1) begin
q = 3'b000;
end
else begin
case(sel)
1'b0: q = q+1;
1'b1: q = q-1;
endcase
end
end
endmodule

verilog/updownmod8_1.0/tmp/individual_14.sv
module individual_14(input wire clk, input wire rst, input wire sel, output reg [2:0] q);
always @(posedge clk) begin
if(rst == 1) begin
q = 3'b000;
end
else begin
case(sel)
1'b0: q = q+1;
1'b1: q = q-1;
endcase
end
end
endmodule

verilog/updownmod8_1.0/tmp/individual_11.sv
module individual_11(input wire clk, input wire rst, input wire sel, output reg [2:0] q);
always @(posedge clk) begin
if(rst == 1) begin
q = 3'b000;
end
else begin
case(sel)
1'b0: q = q+1;
1'b1: q = q-1;
endcase
end
end
endmodule

verilog/updownmod8_1.0/tmp/individual_10.sv
module individual_10(input wire clk, input wire rst, input wire sel, output reg [2:0] q);
always @(posedge clk) begin
if(rst == 1) begin
q = 3'b000;
end
else begin
case(sel)
1'b0: q = q+1;
1'b1: q = q-1;
endcase
end
end
endmodule

verilog/updownmod8_1.0/tmp/testbench.sv
// Declare timescale
`timescale 1ms/1us

// Include all individivuals
`include "tmp/individual_10.sv"
`include "tmp/individual_11.sv"
`include "tmp/individual_14.sv"
`include "tmp/individual_15.sv"
`include "tmp/individual_16.sv"
`include "tmp/individual_17.sv"
`include "tmp/individual_18.sv"
`include "tmp/individual_19.sv"


// Definitions
`define POPULATION_SIZE 20
`define TEST_COUNT 20
`define PERIOD 10
`define CYCLES_PER_TEST 1

// Use parameter to pass population size to testbench
module testbench();
  // Use integer array to store fitness for all individuals
  integer fitness[`POPULATION_SIZE];
  integer run_test;

  // Define inputs and outputs to connect to the individuals
  reg clk;
  reg rst;
  	reg sel;
	reg [2:0] q_expected;
	wire [2:0] q_current[`POPULATION_SIZE];


	// Array of testvectors to store expected values
	reg [4:0] testvectors[0:(`TEST_COUNT-1)];
	integer vectornum = 0;

	// Instantiate all the individuals
    individual_10 dut_10(.clk(clk), .rst(rst), .sel(sel), .q(q_current[10]));
  individual_11 dut_11(.clk(clk), .rst(rst), .sel(sel), .q(q_current[11]));
  individual_14 dut_14(.clk(clk), .rst(rst), .sel(sel), .q(q_current[14]));
  individual_15 dut_15(.clk(clk), .rst(rst), .sel(sel), .q(q_current[15]));
  individual_16 dut_16(.clk(clk), .rst(rst), .sel(sel), .q(q_current[16]));
  individual_17 dut_17(.clk(clk), .rst(rst), .sel(sel), .q(q_current[17]));
  individual_18 dut_18(.clk(clk), .rst(rst), .sel(sel), .q(q_current[18]));
  individual_19 dut_19(.clk(clk), .rst(rst), .sel(sel), .q(q_current[19]));


	// Create task to evaluate each testcase
	// Note that this evaluates the entire population for this testcase
	task testcase;
    input sel_value;
		input [2:0] q_value;


		// Initialise inputs
    		sel=sel_value;


    // Wait for signals to settle
		#0 for(int i = 0; i < `POPULATION_SIZE; i++) begin
            if(q_current[i] == q_value) begin
          fitness[i] = fitness[i] + 1;
      end


		end
	endtask

  // Load our test vectors on the negative edge so that we are ready to run
  // the tests on positive edge
	always @(negedge clk) begin
		if (rst == 0) begin
      // Run test if enough cycles have passed
      if(run_test == `CYCLES_PER_TEST) begin
			{sel, q_expected} = testvectors[vectornum];
			vectornum = vectornum + 1;
      run_test = 1;
      end
      else begin
        run_test++;
      end
    end
	end

  // Run tests on posedge
  always @(posedge clk) begin
		if (rst == 0) begin
      if(run_test == `CYCLES_PER_TEST) begin
        testcase(sel, q_expected);
      end
    end
  end

  // We use a clock to load in our testvectors
  always begin
    #(`PERIOD/2) clk = ~clk;
  end

  // Run simulation
  initial begin
    // DEBUGGING - Dump to vcd file
    $dumpfile("testbench_values.vcd");
    $dumpvars(0,testbench);

    // Read in test vectors
    $readmemb("template/test_vectors.tv", testvectors);

    // Set all scores to zero
    for(int i = 0; i < `POPULATION_SIZE; i++) begin
      fitness[i] = 0;
    end

    // Ensure that the tests run the first clock after reset goes low
    run_test = `CYCLES_PER_TEST;

    // Set the clock high so we get posedges at 10,20,30 etc.
    clk = 0; rst = 1;
    #(`PERIOD) rst = 0;
     
    // Wait 8 clock cycles for test to complete
    #(`PERIOD*`TEST_COUNT+1);

    // Print all fitness scores to the console
    for(int i = 0; i < `POPULATION_SIZE; i++) begin
      $display("%0d",fitness[i]);
    end

    // Finish Simulation
    $finish;
  end
 endmodule

verilog/updownmod8_1.0/testbench_values.vcd
$date
	Mon Apr 19 18:13:41 2021
$end
$version
	Icarus Verilog
$end
$timescale
	1us
$end
$scope module testbench $end
$var reg 1 ! clk $end
$var reg 3 " q_expected [2:0] $end
$var reg 1 # rst $end
$var reg 1 $ sel $end
$var integer 32 % run_test [31:0] $end
$var integer 32 & vectornum [31:0] $end
$scope module dut_10 $end
$var wire 1 ! clk $end
$var wire 1 # rst $end
$var wire 1 $ sel $end
$var reg 3 ' q [2:0] $end
$upscope $end
$scope module dut_11 $end
$var wire 1 ! clk $end
$var wire 1 # rst $end
$var wire 1 $ sel $end
$var reg 3 ( q [2:0] $end
$upscope $end
$scope module dut_14 $end
$var wire 1 ! clk $end
$var wire 1 # rst $end
$var wire 1 $ sel $end
$var reg 3 ) q [2:0] $end
$upscope $end
$scope module dut_15 $end
$var wire 1 ! clk $end
$var wire 1 # rst $end
$var wire 1 $ sel $end
$var reg 3 * q [2:0] $end
$upscope $end
$scope module dut_16 $end
$var wire 1 ! clk $end
$var wire 1 # rst $end
$var wire 1 $ sel $end
$var reg 3 + q [2:0] $end
$upscope $end
$scope module dut_17 $end
$var wire 1 ! clk $end
$var wire 1 # rst $end
$var wire 1 $ sel $end
$var reg 3 , q [2:0] $end
$upscope $end
$scope module dut_18 $end
$var wire 1 ! clk $end
$var wire 1 # rst $end
$var wire 1 $ sel $end
$var reg 3 - q [2:0] $end
$upscope $end
$scope module dut_19 $end
$var wire 1 ! clk $end
$var wire 1 # rst $end
$var wire 1 $ sel $end
$var reg 3 . q [2:0] $end
$upscope $end
$scope begin $ivl_for_loop1 $end
$var integer 32 / i [31:0] $end
$upscope $end
$scope begin $ivl_for_loop2 $end
$var integer 32 0 i [31:0] $end
$upscope $end
$scope task testcase $end
$var reg 3 1 q_value [2:0] $end
$var reg 1 2 sel_value $end
$scope begin $ivl_for_loop0 $end
$var integer 32 3 i [31:0] $end
$upscope $end
$upscope $end
$upscope $end
$enddefinitions $end
#0
$dumpvars
b0 3
x2
bx 1
b0 0
b10100 /
bx .
bx -
bx ,
bx +
bx *
bx )
bx (
bx '
b0 &
b1 %
x$
1#
bx "
0!
$end
#5000
b0 '
b0 (
b0 )
b0 *
b0 +
b0 ,
b0 -
b0 .
1!
#10000
b1 &
0$
b1 "
0!
0#
#15000
b10100 3
b1 1
02
b1 .
b1 -
b1 ,
b1 +
b1 *
b1 )
b1 (
b1 '
1!
#20000
b10 &
b10 "
0!
#25000
b10100 3
b10 '
b10 (
b10 )
b10 *
b10 +
b10 ,
b10 -
b10 .
b10 1
1!
#30000
b11 &
b11 "
0!
#35000
b10100 3
b11 .
b11 -
b11 ,
b11 +
b11 *
b11 )
b11 (
b11 '
b11 1
1!
#40000
b100 &
b100 "
0!
#45000
b10100 3
b100 '
b100 (
b100 )
b100 *
b100 +
b100 ,
b100 -
b100 .
b100 1
1!
#50000
b101 &
b101 "
0!
#55000
b10100 3
b101 .
b101 -
b101 ,
b101 +
b101 *
b101 )
b101 (
b101 '
b101 1
1!
#60000
b110 &
b110 "
0!
#65000
b10100 3
b110 '
b110 (
b110 )
b110 *
b110 +
b110 ,
b110 -
b110 .
b110 1
1!
#70000
b111 &
b111 "
0!
#75000
b10100 3
b111 .
b111 -
b111 ,
b111 +
b111 *
b111 )
b111 (
b111 '
b111 1
1!
#80000
b1000 &
b0 "
0!
#85000
b10100 3
b0 '
b0 (
b0 )
b0 *
b0 +
b0 ,
b0 -
b0 .
b0 1
1!
#90000
b1001 &
b1 "
0!
#95000
b10100 3
b1 .
b1 -
b1 ,
b1 +
b1 *
b1 )
b1 (
b1 '
b1 1
1!
#100000
b1010 &
1$
b0 "
0!
#105000
b10100 3
b0 '
b0 (
b0 )
b0 *
b0 +
b0 ,
b10 -
b0 .
b0 1
12
1!
#110000
b1011 &
b111 "
0!
#115000
b10100 3
b111 .
b11 -
b111 ,
b111 +
b111 *
b111 )
b111 (
b111 '
b111 1
1!
#120000
b1100 &
b110 "
0!
#125000
b10100 3
b110 '
b110 (
b110 )
b110 *
b110 +
b110 ,
b100 -
b110 .
b110 1
1!
#130000
b1101 &
b101 "
0!
#135000
b10100 3
b101 .
b101 -
b101 ,
b101 +
b101 *
b101 )
b101 (
b101 '
b101 1
1!
#140000
b1110 &
b100 "
0!
#145000
b10100 3
b100 '
b100 (
b100 )
b100 *
b100 +
b100 ,
b110 -
b100 .
b100 1
1!
#150000
b1111 &
b11 "
0!
#155000
b10100 3
b11 .
b111 -
b11 ,
b11 +
b11 *
b11 )
b11 (
b11 '
b11 1
1!
#160000
b10000 &
b10 "
0!
#165000
b10100 3
b10 '
b10 (
b10 )
b10 *
b10 +
b10 ,
b0 -
b10 .
b10 1
1!
#170000
b10001 &
b1 "
0!
#175000
b10100 3
b1 .
b1 -
b1 ,
b1 +
b1 *
b1 )
b1 (
b1 '
b1 1
1!
#180000
b10010 &
b0 "
0!
#185000
b10100 3
b0 '
b0 (
b0 )
b0 *
b0 +
b0 ,
b10 -
b0 .
b0 1
1!
#190000
b10011 &
0$
b1 "
0!
#195000
b10100 3
b1 .
b11 -
b1 ,
b1 +
b1 *
b1 )
b1 (
b1 '
b1 1
02
1!
#200000
b10100 &
b10 "
0!
#205000
b10100 3
b10 '
b10 (
b10 )
b10 *
b10 +
b10 ,
b100 -
b10 .
b10 1
1!
#210000
b10101 &
x$
bx "
0!
#211000
b10100 0
